{"name":"Register a new user successfully","id":"user-registration;register-a-new-user-successfully","scenarioId":"UserRegistration:Register a new user successfully","methodName":"Register a new user successfully","testSteps":[{"number":1,"description":"Given I am on the users tab as an administrator","duration":17865,"startTime":"2025-11-28T20:18:30.802007500-05:00[America/Bogota]","result":"SUCCESS","precondition":false,"level":0,"children":[{"number":2,"description":"Danieljose open the","duration":5052,"startTime":"2025-11-28T20:18:31.093981700-05:00[America/Bogota]","result":"SUCCESS","precondition":false,"level":1,"children":[{"number":3,"description":"DanielJose opens the Login page","duration":5024,"startTime":"2025-11-28T20:18:31.114977800-05:00[America/Bogota]","result":"SUCCESS","precondition":false,"level":2}]},{"number":4,"description":"Danieljose do the","duration":12502,"startTime":"2025-11-28T20:18:36.159923100-05:00[America/Bogota]","result":"SUCCESS","precondition":false,"level":1,"children":[{"number":5,"description":"Danieljose put the","duration":12487,"startTime":"2025-11-28T20:18:36.170927300-05:00[America/Bogota]","result":"SUCCESS","precondition":false,"level":2,"children":[{"number":6,"description":"DanielJose enters \u0027admin@couriersync.com\u0027 into Put email in the login","duration":185,"startTime":"2025-11-28T20:18:39.187639800-05:00[America/Bogota]","result":"SUCCESS","precondition":false,"level":3},{"number":7,"description":"DanielJose enters \u0027admin123\u0027 into Put password in the login","duration":101,"startTime":"2025-11-28T20:18:42.390638300-05:00[America/Bogota]","result":"SUCCESS","precondition":false,"level":3},{"number":8,"description":"DanielJose clicks on Press the Acceder button","duration":132,"startTime":"2025-11-28T20:18:45.509506800-05:00[America/Bogota]","result":"SUCCESS","precondition":false,"level":3}]}]}]},{"number":9,"description":"When I select register new user and fill all the required data","duration":35267,"startTime":"2025-11-28T20:18:48.667013700-05:00[America/Bogota]","result":"SUCCESS","precondition":false,"level":0,"children":[{"number":10,"description":"Danieljose enter to","duration":35256,"startTime":"2025-11-28T20:18:48.675011600-05:00[America/Bogota]","result":"SUCCESS","precondition":false,"level":1,"children":[{"number":11,"description":"Danieljose click to","duration":35245,"startTime":"2025-11-28T20:18:48.682014900-05:00[America/Bogota]","result":"SUCCESS","precondition":false,"level":2,"children":[{"number":12,"description":"DanielJose clicks on Press Usuarios Button","duration":113,"startTime":"2025-11-28T20:18:48.687014500-05:00[America/Bogota]","result":"SUCCESS","precondition":false,"level":3},{"number":13,"description":"DanielJose clicks on Press Registrar Usuario Button","duration":111,"startTime":"2025-11-28T20:18:53.820624200-05:00[America/Bogota]","result":"SUCCESS","precondition":false,"level":3},{"number":14,"description":"DanielJose enters \u0027Alejandro Cano\u0027 into Input name","duration":124,"startTime":"2025-11-28T20:18:58.950265700-05:00[America/Bogota]","result":"SUCCESS","precondition":false,"level":3},{"number":15,"description":"DanielJose enters \u0027AleC@gmail.com\u0027 into Input email","duration":90,"startTime":"2025-11-28T20:19:01.086723700-05:00[America/Bogota]","result":"SUCCESS","precondition":false,"level":3},{"number":16,"description":"DanielJose enters \u0027654321\u0027 into Input phone number","duration":84,"startTime":"2025-11-28T20:19:03.187331500-05:00[America/Bogota]","result":"SUCCESS","precondition":false,"level":3},{"number":17,"description":"DanielJose enters \u0027654321\u0027 into Input phone number","duration":79,"startTime":"2025-11-28T20:19:05.276905500-05:00[America/Bogota]","result":"SUCCESS","precondition":false,"level":3},{"number":18,"description":"DanielJose clicks on Input rol","duration":119,"startTime":"2025-11-28T20:19:07.367911200-05:00[America/Bogota]","result":"SUCCESS","precondition":false,"level":3},{"number":19,"description":"DanielJose clicks on Opción de rol","duration":114,"startTime":"2025-11-28T20:19:07.487915900-05:00[America/Bogota]","result":"SUCCESS","precondition":false,"level":3},{"number":20,"description":"DanielJose enters \u0027alejo123\u0027 into Input password","duration":88,"startTime":"2025-11-28T20:19:09.622497500-05:00[America/Bogota]","result":"SUCCESS","precondition":false,"level":3},{"number":21,"description":"DanielJose enters \u0027alejo123\u0027 into Input confirm password","duration":86,"startTime":"2025-11-28T20:19:11.730939900-05:00[America/Bogota]","result":"SUCCESS","precondition":false,"level":3},{"number":22,"description":"DanielJose clicks on Press Registrar Usuario Button","duration":93,"startTime":"2025-11-28T20:19:13.823082900-05:00[America/Bogota]","result":"SUCCESS","precondition":false,"level":3}]}]}]},{"number":23,"description":"Then The new user should be created successfully","duration":99,"startTime":"2025-11-28T20:19:23.935371700-05:00[America/Bogota]","result":"SUCCESS","precondition":false,"level":0,"children":[{"number":24,"description":"Then validation should be a string containing \u0027Alejandro Cano\u0027","duration":34,"startTime":"2025-11-28T20:19:23.996359200-05:00[America/Bogota]","result":"SUCCESS","precondition":false,"level":1}]}],"userStory":{"id":"UserRegistration","storyName":"User Registration","displayName":"User Registration","path":"UserRegistration","pathElements":[{"name":"UserRegistration","description":""}],"narrative":"  As an admin I want to register new users to grant access to the application","type":"feature"},"title":"Register a new user successfully","description":"","tags":[{"name":"Chrome","type":"context","displayName":"Chrome"},{"name":"Windows","type":"context","displayName":"Windows"},{"name":"Chrome, Windows","type":"context","displayName":"Chrome, Windows"}],"startTime":"2025-11-28T20:18:30.697014600-05:00[America/Bogota]","duration":5434,"projectKey":"","sessionId":"ae7deb6e1a4c16568a571fda36f34c73","driver":"chrome","isManualTestingUpToDate":false,"context":"chrome,windows","manual":false,"testSource":"Cucumber","actors":[{"name":"DanielJose","can":["browse the web"]}],"order":0,"result":"SUCCESS"}